MANIFEST.in
README.rst
setup.py
streql.c
pypy/streql.py
streql.egg-info/PKG-INFO
streql.egg-info/SOURCES.txt
streql.egg-info/dependency_links.txt
streql.egg-info/not-zip-safe
streql.egg-info/top_level.txt